{"house":{"houseid":50102,"world":"Kalibra","name":"Castle Shop 2","type":"guildhall","beds":1,"size":42,"rent":1890,"img":"https:\/\/api.tibiadata.com\/statictibiacom\/houses_images_houses_house_50102.jpg","status":{"occupied":false,"auction":true,"owner_now":"Tatudo Kalibrado","owner_new":null,"current_bid":400001,"auction_end":{"date":"2019-01-15 10:00:00.000000","timezone_type":2,"timezone":"CET"},"paid_until":null,"moving_date":null,"transfer_accept":false,"transfer_bid":null,"original":"The house is currently being auctioned. The auction will end at Jan 15 2019, 10:00:00 CET. The highest bid so far is 400001 gold and has been submitted by Tatudo Kalibrado."}},"information":{"api_version":2,"execution_time":0.0003,"last_updated":"2019-01-14 01:23:18","timestamp":"2019-01-14 01:25:23"}}